<?xml version="1.0" encoding="UTF-8"?>
<dmz>
<runtime>
   <time>
      <frequency value="60.0"/>
   </time>
   <state name="Dead"/>
   <object-type name="ground-vehicle"/>
   <object-type name="car" parent="ground-vehicle"/>
   <object-type name="truck" parent="ground-vehicle"/>
   <object-type name="tank" parent="ground-vehicle"/>
</runtime>
<plugin-list>
   <plugin name="dmzPluginConsole"/>
   <plugin name="dmzObjectModuleBasic"/>
<!--
   <plugin name="dmzObjectPluginDump"/>
   <plugin name="dmzPluginMsgDump"/>
-->
   <plugin name="dmzJsModuleV8Basic" scope="javascript"/>
   <plugin name="dmzJsModuleTypesV8Basic" scope="javascript"/>
   <plugin name="dmzJsModuleRuntimeV8Basic" scope="javascript"/>
   <plugin name="dmzJsExtV8Object" scope="javascript"/>
   <plugin name="dmzJsPluginV8ConsoleQt" scope="javascript"/>
   <plugin name="dmzObjectModuleGridBasic"/>
</plugin-list>
<javascript>
   <path value="./scripts"/>
   <path value="../../scripts"/>
   <instance name="object"/>
   <instance name="show"/>
</javascript>
<!-- <dmzObjectModuleGridBasic>
   <grid>
      <cell x="1" y="1"/>
      <min x="0" y="0" z="0"/>
      <max x="40" y="40" z="40"/>
   </grid>
</dmzObjectModuleGridBasic> -->
</dmz>
